README.md
setup.py
sceance/__init__.py
sceance/__main__.py
sceance/file_helpers.py
sceance/film_to_cal.py
sceance/filter_select_showings.py
sceance/get_showings.py
sceance/load_config.py
sceance/set_theaters.py
sceance/set_watchlist.py
sceance/showtimes_to_google_cal.py
sceance/update_watchlist.py
sceance.egg-info/PKG-INFO
sceance.egg-info/SOURCES.txt
sceance.egg-info/dependency_links.txt
sceance.egg-info/entry_points.txt
sceance.egg-info/requires.txt
sceance.egg-info/top_level.txt
sceance/data/credentials.json
sceance/data/settings.ini
sceance/data/timezones.txt
sceance/data/theaters/new-york-theaters.txt
sceance/data/theaters/paris-theaters.txt
sceance/data/theaters/san-francisco-theaters.txt
sceance/data/watchlists/cannes-watchlist.txt
sceance/data/watchlists/criterion-watchlist.txt
sceance/data/watchlists/oscar-winners-watchlist.txt
sceance/data/watchlists/samuel-mignot-watchlist.txt