Metadata-Version: 2.1
Name: sceance
Version: 1.0.0
Summary: Uses a watchlist and favorite theaters to suggest film screenings.
Home-page: https://github.com/sjmignot/sceance
Author: Samuel Mignot
Author-email: sjmignot@gmail.com
License: MIT
Download-URL: https://github.com/sjmignot/sceance/archive/v_01.tar.gz
Keywords: movie theater,showtimes,selenium,movies,film
Platform: UNKNOWN
Classifier: Development Status :: 3 - Alpha
Classifier: Intended Audience :: Developers
Classifier: License :: OSI Approved :: MIT License
